README.rst
setup.py
pypicgo_blind_watermark_plugin/__init__.py
pypicgo_blind_watermark_plugin.egg-info/PKG-INFO
pypicgo_blind_watermark_plugin.egg-info/SOURCES.txt
pypicgo_blind_watermark_plugin.egg-info/dependency_links.txt
pypicgo_blind_watermark_plugin.egg-info/requires.txt
pypicgo_blind_watermark_plugin.egg-info/top_level.txt