Metadata-Version: 2.1
Name: pypicgo-blind-watermark-plugin
Version: 1.0.3
Summary: blind-watermark for pypicgo
Home-page: https://github.com/AnsGoo/pypicgo-blind-watermark-plugin
Author: ansgoo
Author-email: haiven_123@163.com
License: MIT Licence
Keywords: python,pypicgo,blind-watermark,watermark
Platform: any
Classifier: Development Status :: 5 - Production/Stable
Classifier: Programming Language :: Python
Classifier: Programming Language :: Python :: 3
Classifier: Programming Language :: Python :: 3 :: Only
Classifier: Programming Language :: Python :: 3.7
Classifier: Programming Language :: Python :: 3.8
Classifier: Programming Language :: Python :: 3.9
Classifier: Programming Language :: Python :: 3.10
Classifier: License :: OSI Approved :: MIT License
Classifier: Operating System :: Unix
Classifier: Operating System :: POSIX :: Linux
Classifier: Environment :: Console
Classifier: Environment :: MacOS X
